github_traffic_stats-1.2.0.dist-info/METADATA
github_traffic_stats-1.2.0.dist-info/RECORD
github_traffic_stats-1.2.0.dist-info/WHEEL
github_traffic_stats-1.2.0.dist-info/entry_points.txt
github_traffic_stats-1.2.0.dist-info/top_level.txt
gts/__init__.py
gts/__main__.py
gts/main.py
