Metadata-Version: 2.1
Name: github-traffic-stats
Version: 1.2.0
Summary: Get statistics on web traffic to your GitHub repositories.
Home-page: https://github.com/nchah/github-traffic-stats
Author: Niel Chah, Anthony Bloomer
Author-email: UNKNOWN
License: UNKNOWN
Keywords: github,traffic,api
Platform: UNKNOWN
Classifier: Intended Audience :: Developers
Requires-Dist: requests
